promptbench/__init__.py
promptbench/config.py
promptbench/dataload/__init__.py
promptbench/dataload/dataload.py
promptbench/dataload/dataset.py
promptbench/dyval/__init__.py
promptbench/dyval/dyval_dataset.py
promptbench/dyval/dyval_utils.py
promptbench/metrics/__init__.py
promptbench/metrics/eval.py
promptbench/models/__init__.py
promptbench/models/models.py
promptbench/prompt_attack/__init__.py
promptbench/prompt_attack/attack.py
promptbench/prompt_attack/goal_function.py
promptbench/prompt_attack/label_constraint.py
promptbench/prompt_attack/search.py
promptbench/prompt_attack/transformations.py
promptbench/prompt_engineering/__init__.py
promptbench/prompt_engineering/base.py
promptbench/prompt_engineering/chain_of_thought.py
promptbench/prompt_engineering/emotion_prompt.py
promptbench/prompt_engineering/expert_prompting.py
promptbench/prompt_engineering/generated_knowledge.py
promptbench/prompt_engineering/least_to_most.py
promptbench/prompts/__init__.py
promptbench/prompts/method_oriented.py
promptbench/prompts/prompt.py
promptbench/prompts/role_oriented.py
promptbench/prompts/semantic_atk_prompts.py
promptbench/prompts/task_oriented.py
promptbench/utils/__init__.py
promptbench/utils/dataprocess.py
promptbench/utils/defense.py
promptbench/utils/visualize.py
promptbench-0.0.4.dist-info/LICENSE
promptbench-0.0.4.dist-info/METADATA
promptbench-0.0.4.dist-info/WHEEL
promptbench-0.0.4.dist-info/top_level.txt
promptbench-0.0.4.dist-info/RECORD
