Metadata-Version: 2.1
Name: promptbench
Version: 0.0.4
Summary: PromptBench is a powerful tool designed to scrutinize and analyze the interaction of large language models with various prompts. It provides a convenient infrastructure to simulate **black-box** adversarial  **prompt attacks** on the models and evaluate their performances.
Home-page: https://github.com/microsoft/promptbench
Author: 
Author-email: 
Keywords: pytorch,large language models,prompt tuning,dyval,evaluation
Requires-Python: >=3.9
License-File: LICENSE
Requires-Dist: autocorrect ==2.6.1
Requires-Dist: accelerate ==0.25.0
Requires-Dist: datasets >=2.15.0
Requires-Dist: nltk ==3.8.1
Requires-Dist: openai ==1.3.7
Requires-Dist: sentencepiece ==0.1.99
Requires-Dist: tokenizers ==0.15.0
Requires-Dist: torch >=2.1.1
Requires-Dist: tqdm ==4.66.1
Requires-Dist: transformers ==4.38.0
Requires-Dist: Pillow ==10.3.0
Requires-Dist: google-generativeai ==0.4.0
Requires-Dist: dashscope ==1.14.1
Requires-Dist: einops ==0.7.0
Requires-Dist: transformers-stream-generator ==0.0.5
Requires-Dist: torchvision ==0.17.0
Requires-Dist: matplotlib ==3.8.3
Requires-Dist: tiktoken ==0.6.0
